animaltrackingdata/__init__.py
animaltrackingdata/anitra/__init__.py
animaltrackingdata/anitra/tracking.py
animaltrackingdata/anitra/api/__init__.py
animaltrackingdata/anitra/api/api.py
animaltrackingdata/anitra/api/apiwrapper.py
animaltrackingdata/common/__init__.py
animaltrackingdata/common/params.py
animaltrackingdata/common/scroll.py
animaltrackingdata/formatters/__init__.py
animaltrackingdata/formatters/csv.py
animaltrackingdata/formatters/formatter.py
animaltrackingdata/formatters/xlsx.py
animaltrackingdata/movebank/__init__.py
animaltrackingdata-1.0.2.dist-info/LICENSE
animaltrackingdata-1.0.2.dist-info/METADATA
animaltrackingdata-1.0.2.dist-info/WHEEL
animaltrackingdata-1.0.2.dist-info/top_level.txt
animaltrackingdata-1.0.2.dist-info/RECORD
