Metadata-Version: 2.1
Name: animaltrackingdata
Version: 1.0.2
Summary: Animal tracking data source & formatter
Author: Karel Douda
Author-email: karel.douda@anitra.cz
Keywords: anitra,movebank,animal tracking,animal data
Classifier: Development Status :: 3 - Alpha
License-File: LICENSE
Requires-Dist: requests
Requires-Dist: XlsxWriter
